bkps/__init__.py
dload/__init__.py
dload-0.7.0.dist-info/licenses/LICENSE
dload-0.7.0.dist-info/METADATA
dload-0.7.0.dist-info/WHEEL
dload-0.7.0.dist-info/top_level.txt
dload-0.7.0.dist-info/RECORD
